{
  "parent": "minecraft:recipes/root",
  "rewards": {
    "recipes": [
      "chocolate:chocolate_bucket"
    ]
  },
  "criteria": {
    "has_chocolate": {
      "trigger": "minecraft:inventory_changed",
      "conditions": {
        "items": [
          {
            "items": [
              "chocolate:chocolate"
            ]
          }
        ]
      }
    },
    "has_the_recipe": {
      "trigger": "minecraft:recipe_unlocked",
      "conditions": {
        "recipe": "chocolate:chocolate_bucket"
      }
    }
  },
  "requirements": [
    [
      "has_chocolate",
      "has_the_recipe"
    ]
  ]
}